bcrypt_speed_tests/__init__.py
bcrypt_speed_tests/benchmark.py
bcrypt_speed_tests/main.py
bcrypt_speed_tests-0.2.0.dist-info/WHEEL
bcrypt_speed_tests-0.2.0.dist-info/entry_points.txt
bcrypt_speed_tests-0.2.0.dist-info/METADATA
bcrypt_speed_tests-0.2.0.dist-info/RECORD
