Metadata-Version: 2.3
Name: bcrypt-speed-tests
Version: 0.2.0
Summary: CLI for benchmarking bcrypt cost factors on local hardware.
Keywords: bcrypt,benchmark,cli,security,passwords
Author: Grant Ramsay
Author-email: Grant Ramsay <seapagan@gmail.com>
License: MIT
Classifier: Development Status :: 3 - Alpha
Classifier: Environment :: Console
Classifier: Intended Audience :: Developers
Classifier: License :: OSI Approved :: MIT License
Classifier: Programming Language :: Python :: 3
Classifier: Programming Language :: Python :: 3 :: Only
Classifier: Programming Language :: Python :: 3.9
Classifier: Programming Language :: Python :: 3.10
Classifier: Programming Language :: Python :: 3.11
Classifier: Programming Language :: Python :: 3.12
Classifier: Programming Language :: Python :: 3.13
Classifier: Topic :: Security
Classifier: Topic :: System :: Benchmark
Requires-Dist: bcrypt>=5.0.0
Requires-Dist: typer>=0.12.0
Requires-Python: >=3.9
Project-URL: Issues, https://github.com/seapagan/bcrypt-speed-tests/issues
Project-URL: Repository, https://github.com/seapagan/bcrypt-speed-tests
